ston/__init__.py
ston/_modidx.py
ston/cons.py
ston/core.py
ston/util.py
ston-0.0.4.dist-info/LICENSE
ston-0.0.4.dist-info/METADATA
ston-0.0.4.dist-info/WHEEL
ston-0.0.4.dist-info/entry_points.txt
ston-0.0.4.dist-info/top_level.txt
ston-0.0.4.dist-info/RECORD
