Metadata-Version: 2.1
Name: ston
Version: 0.0.4
Summary: ston
Home-page: https://github.com/dsm-72/ston
Author: dsm-72
Author-email: sumner.magruder@yale.edu
License: Apache Software License 2.0
Keywords: singleton
Classifier: Development Status :: 4 - Beta
Classifier: Intended Audience :: Developers
Classifier: Natural Language :: English
Classifier: Programming Language :: Python :: 3.11
Classifier: License :: OSI Approved :: Apache Software License
Requires-Python: >=3.11
License-File: LICENSE
Provides-Extra: dev
Requires-Dist: torch ; extra == 'dev'
